Workbook

Sheet Params
A1: LTV/CAC 渠道获客门控 · 参数与口径（改这里，全表自动生效）
A2: 参数项 | B2: 数值 | C2: 单位 | D2: 说明与护栏
A3: 暂停阈值 pause_threshold | B3: 3 | C3: 倍 | D3: 比值 < 3.0：停新客投放预算，仅保留品牌保底
A4: 扩投阈值 boost_threshold | B4: 5 | C4: 倍 | D4: 比值 ≥ 5.0：加投，单渠道单月最多 +20%
A5: 扩投比例 boost_ratio | B5: 0.2 | C5: 倍 | D5: 加投上限 ＝ 当月在投预算 × 该比例
A6: 最小新客数 min_new_customers | B6: 50 | C6: 人 | D6: 当月新客 < 50：样本不足，不评估，维持原预算
A7: 品牌保底预算 min_brand_budget | B7: 500 | C7: 元/月 | D7: 暂停 ≠ 关停：保底只用于品牌词防守与内容留存
A8: 保底预算比例 min_floor_ratio | B8: 0.05 | C8: 倍 | D8: 保底 ＝ max(500 元, 原预算 × 5%)
A9: 暂停观察天数 pause_observation_days | B9: 7 | C9: 天 | D9: 暂停后第 7 天看直搜/自然量，满 30 天必须复评
A10: 连续扩投次数上限 max_boost_rounds | B10: 2 | C10: 次 | D10: 同一渠道连续扩投 2 个月后转人工复核
A11: 数据滞后天数 data_lag_days | B11: 3 | C11: 天 | D11: 每月 3 日前锁上月数据，6 日前出调整指令
A13: 常量（供公式引用，勿改） | B13: 取值 | C13: 单位 | D13: 说明
A14: 释放预算吸收比例 max_absorb_ratio | B14: 1 | C14: 倍 | D14: 高效渠道合计吸收量 ＝ 释放预算；按各渠道加投上限比例分
A15: 总预算硬上限 total_budget_cap | B15: 110000 | C15: 元 | D15: 加投后总盘不得超过此值，超出则按比值截断
E17: 口径（三个数必须同月份、同口径、同币种）
E18: 指标 | F18: 定义
E19: 新客 LTV（12 月）
E20: CAC
E21: 新客数
E22: 当月预算

Sheet 门控矩阵
A1: LTV/CAC 渠道获客门控 · 判定与预算调整指令｜月更只填 A–F 列，G–V 与汇总全自动｜示例月份 2025-08
A2: 月份 | B2: 渠道 | C2: 预测/平滑LTV(元) | D2: CAC(元) | E2: 新客数(人) | F2: 当月预算(元) | G2: 保底预算(元) | H2: 样本门控 | I2: LTV/CAC | J2: 判定 | K2: 释放预算(元) | L2: 吸收上限(元) | M2: 加投上限(元) | N2: 新客预算(元) | O2: 本月调整(元) | P2: 系统指令 | Q2: 复评日 | R2: 谁执行 | S2: 建议转入(元) | T2: 本月新客(预测) | U2: 预算合计(元) | V2: 总盘校验
A3: 2025-07 | B3: 拼多多 | C3: 85 | D3: 40.4 | E3: 120 | F3: 26000 | G3: =ROUND(MAX(Params!$B$7,F3*Params!$B$8),0) -> 1300 | H3: =IF(E3=0,"",IF(E3>=Params!$B$6,"通过","不足")) -> 通过 | I3: =IF(E3=0,"",ROUND(C3/D3,2)) -> 2.1 | J3: =IF(E3=0,"",IF(H3="不足","样本不足",IF(I3>=Params!$B$4,"扩投",IF(I3<Params!$B$3,"暂停","维持")))) -> 暂停 | K3: =IF(F3=0,0,IF(J3="暂停",G3,0)) -> 1300 | L3: =IF(F3=0,0,IF(J3="扩投",F3*1.2,0)) -> 0 | M3: =IF(J3="扩投",ROUND(F3*1.2,0),0) -> 0 | N3: =IF(F3=0,0,IF(J3="暂停",G3,IF(J3="扩投",ROUND(MIN(M3,F3+S3),0),F3))) -> 1300 | O3: =IF(F3=0,0,N3-F3) -> -24700 | P3: =IF(F3=0,"",IF(J3="暂停","停新客投放，仅保品牌词与内容留存","")&IF(J3="扩投","加投至新客预算上限","")&IF(J3="维持","持平，下月复评","")&IF(J3="样本不足","样本不足不评估，维持原预算","")) -> 停新客投放，仅保品牌词与内容留存 | Q3: =IF(J3="暂停",TEXT(DATE(YEAR(A3),MONTH(A3)+1,1)+Params!$B$9-1,"m月d日"),"") -> 8月7日 | R3: =IF(J3="暂停","投放负责人+品牌负责人","")&IF(J3="扩投","投放负责人","") -> 投放负责人+品牌负责人 | S3: =IF(L3>0,ROUND($B$19*M3/$B$20,0),0) -> 0 | T3: =IF(F3=0,0,ROUND(E3*N3/F3,0)) -> 6 | U3: =IF(F3=0,0,N3) -> 1300 | V3: =IF(F3=0,0,IF(E3>0,N3,0)) -> 1300
A4: 2025-07 | B4: 抖音 | C4: 248 | D4: 40 | E4: 320 | F4: 15000 | G4: =ROUND(MAX(Params!$B$7,F4*Params!$B$8),0) -> 750 | H4: =IF(E4=0,"",IF(E4>=Params!$B$6,"通过","不足")) -> 通过 | I4: =IF(E4=0,"",ROUND(C4/D4,2)) -> 6.2 | J4: =IF(E4=0,"",IF(H4="不足","样本不足",IF(I4>=Params!$B$4,"扩投",IF(I4<Params!$B$3,"暂停","维持")))) -> 扩投 | K4: =IF(F4=0,0,IF(J4="暂停",G4,0)) -> 0 | L4: =IF(F4=0,0,IF(J4="扩投",F4*1.2,0)) -> 18000 | M4: =IF(J4="扩投",ROUND(F4*1.2,0),0) -> 18000 | N4: =IF(F4=0,0,IF(J4="暂停",G4,IF(J4="扩投",ROUND(MIN(M4,F4+S4),0),F4))) -> 15750 | O4: =IF(F4=0,0,N4-F4) -> 750 | P4: =IF(F4=0,"",IF(J4="暂停","停新客投放，仅保品牌词与内容留存","")&IF(J4="扩投","加投至新客预算上限","")&IF(J4="维持","持平，下月复评","")&IF(J4="样本不足","样本不足不评估，维持原预算","")) -> 加投至新客预算上限 | Q4: =IF(J4="暂停",TEXT(DATE(YEAR(A4),MONTH(A4)+1,1)+Params!$B$9-1,"m月d日"),"") | R4: =IF(J4="暂停","投放负责人+品牌负责人","")&IF(J4="扩投","投放负责人","") -> 投放负责人 | S4: =IF(L4>0,ROUND($B$19*M4/$B$20,0),0) -> 750 | T4: =IF(F4=0,0,ROUND(E4*N4/F4,0)) -> 336 | U4: =IF(F4=0,0,N4) -> 15750 | V4: =IF(F4=0,0,IF(E4>0,N4,0)) -> 15750 | W4: =IF(F3=0,0,IF(E3>0,N3,0)) -> 1300
A5: 2025-07 | B5: 视频号 | C5: 155 | D5: 33 | E5: 95 | F5: 5000 | G5: =ROUND(MAX(Params!$B$7,F5*Params!$B$8),0) -> 500 | H5: =IF(E5=0,"",IF(E5>=Params!$B$6,"通过","不足")) -> 通过 | I5: =IF(E5=0,"",ROUND(C5/D5,2)) -> 4.7 | J5: =IF(E5=0,"",IF(H5="不足","样本不足",IF(I5>=Params!$B$4,"扩投",IF(I5<Params!$B$3,"暂停","维持")))) -> 维持 | K5: =IF(F5=0,0,IF(J5="暂停",G5,0)) -> 0 | L5: =IF(F5=0,0,IF(J5="扩投",F5*1.2,0)) -> 0 | M5: =IF(J5="扩投",ROUND(F5*1.2,0),0) -> 0 | N5: =IF(F5=0,0,IF(J5="暂停",G5,IF(J5="扩投",ROUND(MIN(M5,F5+S5),0),F5))) -> 5000 | O5: =IF(F5=0,0,N5-F5) -> 0 | P5: =IF(F5=0,"",IF(J5="暂停","停新客投放，仅保品牌词与内容留存","")&IF(J5="扩投","加投至新客预算上限","")&IF(J5="维持","持平，下月复评","")&IF(J5="样本不足","样本不足不评估，维持原预算","")) -> 持平，下月复评 | Q5: =IF(J5="暂停",TEXT(DATE(YEAR(A5),MONTH(A5)+1,1)+Params!$B$9-1,"m月d日"),"") | R5: =IF(J5="暂停","投放负责人+品牌负责人","")&IF(J5="扩投","投放负责人","") | S5: =IF(L5>0,ROUND($B$19*M5/$B$20,0),0) -> 0 | T5: =IF(F5=0,0,ROUND(E5*N5/F5,0)) -> 95 | U5: =IF(F5=0,0,N5) -> 5000 | V5: =IF(F5=0,0,IF(E5>0,N5,0)) -> 5000 | W5: =IF(F4=0,0,IF(E4>0,N4,0)) -> 15750
A6: 2025-07 | B6: 私域社群 | C6: 268 | D6: 44 | E6: 197 | F6: 11000 | G6: =ROUND(MAX(Params!$B$7,F6*Params!$B$8),0) -> 550 | H6: =IF(E6=0,"",IF(E6>=Params!$B$6,"通过","不足")) -> 通过 | I6: =IF(E6=0,"",ROUND(C6/D6,2)) -> 6.09 | J6: =IF(E6=0,"",IF(H6="不足","样本不足",IF(I6>=Params!$B$4,"扩投",IF(I6<Params!$B$3,"暂停","维持")))) -> 扩投 | K6: =IF(F6=0,0,IF(J6="暂停",G6,0)) -> 0 | L6: =IF(F6=0,0,IF(J6="扩投",F6*1.2,0)) -> 13200 | M6: =IF(J6="扩投",ROUND(F6*1.2,0),0) -> 13200 | N6: =IF(F6=0,0,IF(J6="暂停",G6,IF(J6="扩投",ROUND(MIN(M6,F6+S6),0),F6))) -> 11550 | O6: =IF(F6=0,0,N6-F6) -> 550 | P6: =IF(F6=0,"",IF(J6="暂停","停新客投放，仅保品牌词与内容留存","")&IF(J6="扩投","加投至新客预算上限","")&IF(J6="维持","持平，下月复评","")&IF(J6="样本不足","样本不足不评估，维持原预算","")) -> 加投至新客预算上限 | Q6: =IF(J6="暂停",TEXT(DATE(YEAR(A6),MONTH(A6)+1,1)+Params!$B$9-1,"m月d日"),"") | R6: =IF(J6="暂停","投放负责人+品牌负责人","")&IF(J6="扩投","投放负责人","") -> 投放负责人 | S6: =IF(L6>0,ROUND($B$19*M6/$B$20,0),0) -> 550 | T6: =IF(F6=0,0,ROUND(E6*N6/F6,0)) -> 207 | U6: =IF(F6=0,0,N6) -> 11550 | V6: =IF(F6=0,0,IF(E6>0,N6,0)) -> 11550 | W6: =IF(F5=0,0,IF(E5>0,N5,0)) -> 5000
A7: 2025-07 | B7: 小红书 | C7: 198 | D7: 45 | E7: 70 | F7: 12000 | G7: =ROUND(MAX(Params!$B$7,F7*Params!$B$8),0) -> 600 | H7: =IF(E7=0,"",IF(E7>=Params!$B$6,"通过","不足")) -> 通过 | I7: =IF(E7=0,"",ROUND(C7/D7,2)) -> 4.4 | J7: =IF(E7=0,"",IF(H7="不足","样本不足",IF(I7>=Params!$B$4,"扩投",IF(I7<Params!$B$3,"暂停","维持")))) -> 维持 | K7: =IF(F7=0,0,IF(J7="暂停",G7,0)) -> 0 | L7: =IF(F7=0,0,IF(J7="扩投",F7*1.2,0)) -> 0 | M7: =IF(J7="扩投",ROUND(F7*1.2,0),0) -> 0 | N7: =IF(F7=0,0,IF(J7="暂停",G7,IF(J7="扩投",ROUND(MIN(M7,F7+S7),0),F7))) -> 12000 | O7: =IF(F7=0,0,N7-F7) -> 0 | P7: =IF(F7=0,"",IF(J7="暂停","停新客投放，仅保品牌词与内容留存","")&IF(J7="扩投","加投至新客预算上限","")&IF(J7="维持","持平，下月复评","")&IF(J7="样本不足","样本不足不评估，维持原预算","")) -> 持平，下月复评 | Q7: =IF(J7="暂停",TEXT(DATE(YEAR(A7),MONTH(A7)+1,1)+Params!$B$9-1,"m月d日"),"") | R7: =IF(J7="暂停","投放负责人+品牌负责人","")&IF(J7="扩投","投放负责人","") | S7: =IF(L7>0,ROUND($B$19*M7/$B$20,0),0) -> 0 | T7: =IF(F7=0,0,ROUND(E7*N7/F7,0)) -> 70 | U7: =IF(F7=0,0,N7) -> 12000 | V7: =IF(F7=0,0,IF(E7>0,N7,0)) -> 12000 | W7: =IF(F6=0,0,IF(E6>0,N6,0)) -> 11550
A8: 2025-07 | B8: 线下活动 | C8: 176 | D8: 50 | E8: 200 | F8: 10000 | G8: =ROUND(MAX(Params!$B$7,F8*Params!$B$8),0) -> 500 | H8: =IF(E8=0,"",IF(E8>=Params!$B$6,"通过","不足")) -> 通过 | I8: =IF(E8=0,"",ROUND(C8/D8,2)) -> 3.52 | J8: =IF(E8=0,"",IF(H8="不足","样本不足",IF(I8>=Params!$B$4,"扩投",IF(I8<Params!$B$3,"暂停","维持")))) -> 维持 | K8: =IF(F8=0,0,IF(J8="暂停",G8,0)) -> 0 | L8: =IF(F8=0,0,IF(J8="扩投",F8*1.2,0)) -> 0 | M8: =IF(J8="扩投",ROUND(F8*1.2,0),0) -> 0 | N8: =IF(F8=0,0,IF(J8="暂停",G8,IF(J8="扩投",ROUND(MIN(M8,F8+S8),0),F8))) -> 10000 | O8: =IF(F8=0,0,N8-F8) -> 0 | P8: =IF(F8=0,"",IF(J8="暂停","停新客投放，仅保品牌词与内容留存","")&IF(J8="扩投","加投至新客预算上限","")&IF(J8="维持","持平，下月复评","")&IF(J8="样本不足","样本不足不评估，维持原预算","")) -> 持平，下月复评 | Q8: =IF(J8="暂停",TEXT(DATE(YEAR(A8),MONTH(A8)+1,1)+Params!$B$9-1,"m月d日"),"") | R8: =IF(J8="暂停","投放负责人+品牌负责人","")&IF(J8="扩投","投放负责人","") | S8: =IF(L8>0,ROUND($B$19*M8/$B$20,0),0) -> 0 | T8: =IF(F8=0,0,ROUND(E8*N8/F8,0)) -> 200 | U8: =IF(F8=0,0,N8) -> 10000 | V8: =IF(F8=0,0,IF(E8>0,N8,0)) -> 10000 | W8: =IF(F7=0,0,IF(E7>0,N7,0)) -> 12000
A9: 2025-07 | B9: 知乎 | C9: 118 | D9: 40 | E9: 30 | F9: 4000 | G9: =ROUND(MAX(Params!$B$7,F9*Params!$B$8),0) -> 500 | H9: =IF(E9=0,"",IF(E9>=Params!$B$6,"通过","不足")) -> 不足 | I9: =IF(E9=0,"",ROUND(C9/D9,2)) -> 2.95 | J9: =IF(E9=0,"",IF(H9="不足","样本不足",IF(I9>=Params!$B$4,"扩投",IF(I9<Params!$B$3,"暂停","维持")))) -> 样本不足 | K9: =IF(F9=0,0,IF(J9="暂停",G9,0)) -> 0 | L9: =IF(F9=0,0,IF(J9="扩投",F9*1.2,0)) -> 0 | M9: =IF(J9="扩投",ROUND(F9*1.2,0),0) -> 0 | N9: =IF(F9=0,0,IF(J9="暂停",G9,IF(J9="扩投",ROUND(MIN(M9,F9+S9),0),F9))) -> 4000 | O9: =IF(F9=0,0,N9-F9) -> 0 | P9: =IF(F9=0,"",IF(J9="暂停","停新客投放，仅保品牌词与内容留存","")&IF(J9="扩投","加投至新客预算上限","")&IF(J9="维持","持平，下月复评","")&IF(J9="样本不足","样本不足不评估，维持原预算","")) -> 样本不足不评估，维持原预算 | Q9: =IF(J9="暂停",TEXT(DATE(YEAR(A9),MONTH(A9)+1,1)+Params!$B$9-1,"m月d日"),"") | R9: =IF(J9="暂停","投放负责人+品牌负责人","")&IF(J9="扩投","投放负责人","") | S9: =IF(L9>0,ROUND($B$19*M9/$B$20,0),0) -> 0 | T9: =IF(F9=0,0,ROUND(E9*N9/F9,0)) -> 30 | U9: =IF(F9=0,0,N9) -> 4000 | V9: =IF(F9=0,0,IF(E9>0,N9,0)) -> 4000 | W9: =IF(F8=0,0,IF(E8>0,N8,0)) -> 10000
A10: 2025-07 | B10: B站 | C10: 210 | D10: 46 | E10: 60 | F10: 6000 | G10: =ROUND(MAX(Params!$B$7,F10*Params!$B$8),0) -> 500 | H10: =IF(E10=0,"",IF(E10>=Params!$B$6,"通过","不足")) -> 通过 | I10: =IF(E10=0,"",ROUND(C10/D10,2)) -> 4.57 | J10: =IF(E10=0,"",IF(H10="不足","样本不足",IF(I10>=Params!$B$4,"扩投",IF(I10<Params!$B$3,"暂停","维持")))) -> 维持 | K10: =IF(F10=0,0,IF(J10="暂停",G10,0)) -> 0 | L10: =IF(F10=0,0,IF(J10="扩投",F10*1.2,0)) -> 0 | M10: =IF(J10="扩投",ROUND(F10*1.2,0),0) -> 0 | N10: =IF(F10=0,0,IF(J10="暂停",G10,IF(J10="扩投",ROUND(MIN(M10,F10+S10),0),F10))) -> 6000 | O10: =IF(F10=0,0,N10-F10) -> 0 | P10: =IF(F10=0,"",IF(J10="暂停","停新客投放，仅保品牌词与内容留存","")&IF(J10="扩投","加投至新客预算上限","")&IF(J10="维持","持平，下月复评","")&IF(J10="样本不足","样本不足不评估，维持原预算","")) -> 持平，下月复评 | Q10: =IF(J10="暂停",TEXT(DATE(YEAR(A10),MONTH(A10)+1,1)+Params!$B$9-1,"m月d日"),"") | R10: =IF(J10="暂停","投放负责人+品牌负责人","")&IF(J10="扩投","投放负责人","") | S10: =IF(L10>0,ROUND($B$19*M10/$B$20,0),0) -> 0 | T10: =IF(F10=0,0,ROUND(E10*N10/F10,0)) -> 60 | U10: =IF(F10=0,0,N10) -> 6000 | V10: =IF(F10=0,0,IF(E10>0,N10,0)) -> 6000 | W10: =IF(F9=0,0,IF(E9>0,N9,0)) -> 4000
G11: =ROUND(MAX(Params!$B$7,F11*Params!$B$8),0) -> 500 | H11: =IF(E11=0,"",IF(E11>=Params!$B$6,"通过","不足")) | I11: =IF(E11=0,"",ROUND(C11/D11,2)) | J11: =IF(E11=0,"",IF(H11="不足","样本不足",IF(I11>=Params!$B$4,"扩投",IF(I11<Params!$B$3,"暂停","维持")))) | K11: =IF(F11=0,0,IF(J11="暂停",G11,0)) -> 0 | L11: =IF(F11=0,0,IF(J11="扩投",F11*1.2,0)) -> 0 | M11: =IF(J11="扩投",ROUND(F11*1.2,0),0) -> 0 | N11: =IF(F11=0,0,IF(J11="暂停",G11,IF(J11="扩投",ROUND(MIN(M11,F11+S11),0),F11))) -> 0 | O11: =IF(F11=0,0,N11-F11) -> 0 | P11: =IF(F11=0,"",IF(J11="暂停","停新客投放，仅保品牌词与内容留存","")&IF(J11="扩投","加投至新客预算上限","")&IF(J11="维持","持平，下月复评","")&IF(J11="样本不足","样本不足不评估，维持原预算","")) | Q11: =IF(J11="暂停",TEXT(DATE(YEAR(A11),MONTH(A11)+1,1)+Params!$B$9-1,"m月d日"),"") | R11: =IF(J11="暂停","投放负责人+品牌负责人","")&IF(J11="扩投","投放负责人","") | S11: =IF(L11>0,ROUND($B$19*M11/$B$20,0),0) -> 0 | T11: =IF(F11=0,0,ROUND(E11*N11/F11,0)) -> 0 | U11: =IF(F11=0,0,N11) -> 0 | V11: =IF(F11=0,0,IF(E11>0,N11,0)) -> 0 | W11: =IF(F10=0,0,IF(E10>0,N10,0)) -> 6000
G12: =ROUND(MAX(Params!$B$7,F12*Params!$B$8),0) -> 500 | H12: =IF(E12=0,"",IF(E12>=Params!$B$6,"通过","不足")) | I12: =IF(E12=0,"",ROUND(C12/D12,2)) | J12: =IF(E12=0,"",IF(H12="不足","样本不足",IF(I12>=Params!$B$4,"扩投",IF(I12<Params!$B$3,"暂停","维持")))) | K12: =IF(F12=0,0,IF(J12="暂停",G12,0)) -> 0 | L12: =IF(F12=0,0,IF(J12="扩投",F12*1.2,0)) -> 0 | M12: =IF(J12="扩投",ROUND(F12*1.2,0),0) -> 0 | N12: =IF(F12=0,0,IF(J12="暂停",G12,IF(J12="扩投",ROUND(MIN(M12,F12+S12),0),F12))) -> 0 | O12: =IF(F12=0,0,N12-F12) -> 0 | P12: =IF(F12=0,"",IF(J12="暂停","停新客投放，仅保品牌词与内容留存","")&IF(J12="扩投","加投至新客预算上限","")&IF(J12="维持","持平，下月复评","")&IF(J12="样本不足","样本不足不评估，维持原预算","")) | Q12: =IF(J12="暂停",TEXT(DATE(YEAR(A12),MONTH(A12)+1,1)+Params!$B$9-1,"m月d日"),"") | R12: =IF(J12="暂停","投放负责人+品牌负责人","")&IF(J12="扩投","投放负责人","") | S12: =IF(L12>0,ROUND($B$19*M12/$B$20,0),0) -> 0 | T12: =IF(F12=0,0,ROUND(E12*N12/F12,0)) -> 0 | U12: =IF(F12=0,0,N12) -> 0 | V12: =IF(F12=0,0,IF(E12>0,N12,0)) -> 0 | W12: =IF(F11=0,0,IF(E11>0,N11,0)) -> 0
G13: =ROUND(MAX(Params!$B$7,F13*Params!$B$8),0) -> 500 | H13: =IF(E13=0,"",IF(E13>=Params!$B$6,"通过","不足")) | I13: =IF(E13=0,"",ROUND(C13/D13,2)) | J13: =IF(E13=0,"",IF(H13="不足","样本不足",IF(I13>=Params!$B$4,"扩投",IF(I13<Params!$B$3,"暂停","维持")))) | K13: =IF(F13=0,0,IF(J13="暂停",G13,0)) -> 0 | L13: =IF(F13=0,0,IF(J13="扩投",F13*1.2,0)) -> 0 | M13: =IF(J13="扩投",ROUND(F13*1.2,0),0) -> 0 | N13: =IF(F13=0,0,IF(J13="暂停",G13,IF(J13="扩投",ROUND(MIN(M13,F13+S13),0),F13))) -> 0 | O13: =IF(F13=0,0,N13-F13) -> 0 | P13: =IF(F13=0,"",IF(J13="暂停","停新客投放，仅保品牌词与内容留存","")&IF(J13="扩投","加投至新客预算上限","")&IF(J13="维持","持平，下月复评","")&IF(J13="样本不足","样本不足不评估，维持原预算","")) | Q13: =IF(J13="暂停",TEXT(DATE(YEAR(A13),MONTH(A13)+1,1)+Params!$B$9-1,"m月d日"),"") | R13: =IF(J13="暂停","投放负责人+品牌负责人","")&IF(J13="扩投","投放负责人","") | S13: =IF(L13>0,ROUND($B$19*M13/$B$20,0),0) -> 0 | T13: =IF(F13=0,0,ROUND(E13*N13/F13,0)) -> 0 | U13: =IF(F13=0,0,N13) -> 0 | V13: =IF(F13=0,0,IF(E13>0,N13,0)) -> 0 | W13: =IF(F12=0,0,IF(E12>0,N12,0)) -> 0
G14: =ROUND(MAX(Params!$B$7,F14*Params!$B$8),0) -> 500 | H14: =IF(E14=0,"",IF(E14>=Params!$B$6,"通过","不足")) | I14: =IF(E14=0,"",ROUND(C14/D14,2)) | J14: =IF(E14=0,"",IF(H14="不足","样本不足",IF(I14>=Params!$B$4,"扩投",IF(I14<Params!$B$3,"暂停","维持")))) | K14: =IF(F14=0,0,IF(J14="暂停",G14,0)) -> 0 | L14: =IF(F14=0,0,IF(J14="扩投",F14*1.2,0)) -> 0 | M14: =IF(J14="扩投",ROUND(F14*1.2,0),0) -> 0 | N14: =IF(F14=0,0,IF(J14="暂停",G14,IF(J14="扩投",ROUND(MIN(M14,F14+S14),0),F14))) -> 0 | O14: =IF(F14=0,0,N14-F14) -> 0 | P14: =IF(F14=0,"",IF(J14="暂停","停新客投放，仅保品牌词与内容留存","")&IF(J14="扩投","加投至新客预算上限","")&IF(J14="维持","持平，下月复评","")&IF(J14="样本不足","样本不足不评估，维持原预算","")) | Q14: =IF(J14="暂停",TEXT(DATE(YEAR(A14),MONTH(A14)+1,1)+Params!$B$9-1,"m月d日"),"") | R14: =IF(J14="暂停","投放负责人+品牌负责人","")&IF(J14="扩投","投放负责人","") | S14: =IF(L14>0,ROUND($B$19*M14/$B$20,0),0) -> 0 | T14: =IF(F14=0,0,ROUND(E14*N14/F14,0)) -> 0 | U14: =IF(F14=0,0,N14) -> 0 | V14: =IF(F14=0,0,IF(E14>0,N14,0)) -> 0 | W14: =IF(F13=0,0,IF(E13>0,N13,0)) -> 0
G15: =ROUND(MAX(Params!$B$7,F15*Params!$B$8),0) -> 500 | H15: =IF(E15=0,"",IF(E15>=Params!$B$6,"通过","不足")) | I15: =IF(E15=0,"",ROUND(C15/D15,2)) | J15: =IF(E15=0,"",IF(H15="不足","样本不足",IF(I15>=Params!$B$4,"扩投",IF(I15<Params!$B$3,"暂停","维持")))) | K15: =IF(F15=0,0,IF(J15="暂停",G15,0)) -> 0 | L15: =IF(F15=0,0,IF(J15="扩投",F15*1.2,0)) -> 0 | M15: =IF(J15="扩投",ROUND(F15*1.2,0),0) -> 0 | N15: =IF(F15=0,0,IF(J15="暂停",G15,IF(J15="扩投",ROUND(MIN(M15,F15+S15),0),F15))) -> 0 | O15: =IF(F15=0,0,N15-F15) -> 0 | P15: =IF(F15=0,"",IF(J15="暂停","停新客投放，仅保品牌词与内容留存","")&IF(J15="扩投","加投至新客预算上限","")&IF(J15="维持","持平，下月复评","")&IF(J15="样本不足","样本不足不评估，维持原预算","")) | Q15: =IF(J15="暂停",TEXT(DATE(YEAR(A15),MONTH(A15)+1,1)+Params!$B$9-1,"m月d日"),"") | R15: =IF(J15="暂停","投放负责人+品牌负责人","")&IF(J15="扩投","投放负责人","") | S15: =IF(L15>0,ROUND($B$19*M15/$B$20,0),0) -> 0 | T15: =IF(F15=0,0,ROUND(E15*N15/F15,0)) -> 0 | U15: =IF(F15=0,0,N15) -> 0 | V15: =IF(F15=0,0,IF(E15>0,N15,0)) -> 0 | W15: =IF(F14=0,0,IF(E14>0,N14,0)) -> 0
W16: =IF(F15=0,0,IF(E15>0,N15,0)) -> 0
A18: 汇总（自动） | B18: 数值 | C18: 单位
A19: 暂停渠道释放的预算 | B19: =SUM(K3:K15) -> 1300 | C19: 元/月
A20: 扩投渠道可吸收上限（=加投上限合计） | B20: =SUM(L3:L15) -> 31200 | C20: 元/月
A21: 本月加投金额合计 | B21: =SUM(M3:M15) -> 31200 | C21: 元/月
A22: 调整后新客预算总盘 | B22: =SUM(N3:N15) -> 65600 | C22: 元
A23: 总盘校验（上限 Params!B15） | B23: =IF(SUM(N3:N15)>Params!B15,"超上限：按比值截断加投","通过：未超总盘上限") -> 通过：未超总盘上限

Sheet 执行清单
A1: LTV/CAC 渠道获客门控 · 执行清单｜阈值口径见 Params 页，判定与金额见「门控矩阵」页（示例月份 2025-07）
A2: 一、判定规则（按序判断，命中即停）
A3: 序 | B3: 规则 | C3: 阈值 / 判据 | D3: 动作
A4: 1 | B4: 样本门控 | C4: 当月新客 ≥ 50 人 | D4: 不足则标「样本不足」：不评估、维持原预算（示例中的知乎）
A5: 2 | B5: LTV/CAC 比值 | C5: 平滑 LTV ÷ 当月 CAC（近 3 月移动平均） | D5: 保留 2 位小数，作为唯一判定与排序依据
A6: 3 | B6: 暂停闸门 | C6: 比值 < 3.0 | D6: 停该渠道新客投放预算，只留品牌保底；7 天后看自然量，满 30 天必须复评
A7: 4 | B7: 扩投闸门 | C7: 比值 ≥ 5.0 | D7: 加投至 min(当月预算×1.2, 当月预算 + 释放预算按加投上限分摊额)
A8: 5 | B8: 观察区 | C8: 3.0 ≤ 比值 < 5.0 | D8: 持平不追加；连续 2 个月落在观察区，转人工复核素材与人群
A10: 二、本月预算调整指令（实时取自「门控矩阵」，改矩阵即自动更新）
A11: 暂停渠道释放的预算 | B11: =门控矩阵!B19 -> 1300 | C11: 元/月 | D11: 自动计算 | E11: =IF(门控矩阵!B23="通过：未超总盘上限","✔ 未超总盘上限","✘ 超上限：按比值截断加投") -> ✔ 未超总盘上限
A12: 扩投渠道可吸收上限（加投上限合计） | B12: =门控矩阵!B20 -> 31200 | C12: 元/月 | D12: 自动计算
A13: 本月加投金额合计 | B13: =门控矩阵!B21 -> 31200 | C13: 元/月 | D13: 自动计算
A14: 调整后新客预算总盘 | B14: =门控矩阵!B22 -> 65600 | C14: 元 | D14: 自动计算
A15: 总盘上限（110%） | B15: =Params!B15 -> 110000 | C15: 元 | D15: 自动计算
A16: 其中：品牌保底预留（暂停渠道） | B16: =SUM(门控矩阵!G3:G15) -> 7700 | C16: 元/月 | D16: 自动计算
A18: 三、每月 6 步闭环（谁在哪天做什么）
A19: D3 | B19: 锁数 | C19: — | D19: 结算月 3 日前冻结各渠道 LTV / CAC / 新客数 / 当月预算；数据不全的渠道一律标「样本不足」
A20: D4-5 | B20: 跑门控 | C20: — | D20: 在「门控矩阵」A–F 列填数，G–V 与汇总自动出判定与金额；逐行核对系统指令栏
A21: D6 | B21: 批指令 | C21: — | D21: 投放负责人确认暂停/加投清单，品牌负责人确认保底金额，形成当月一张预算调整单
A22: D25-31 | B22: 执行 | C22: — | D22: 渠道后台改预算与出价；暂停渠道只保留品牌词防守与内容留存，不得整店关停
A23: D+7 | B23: 看护 | C23: — | D23: 暂停渠道第 7 天看品牌直搜量与自然进店量，跌幅超 15% 则把保底上调至原预算的 10%
A24: D30 | B24: 复评 | C24: — | D24: 满 30 天强制复评：比值回到 ≥ 3.0 才恢复投放，否则进入下一轮观察或改素材与人群
A26: 四、硬约束（越线即停，防止跑飞）
A27: 暂停 ≠ 关停 | B27: 任何渠道暂停后必须留保底 = max(500 元, 原预算 × 5%)，用于品牌词防守与内容留存
A28: 暂停有时限 | B28: 单次暂停最长 30 天必须复评，观察期 7 天；禁止一次性永久关停渠道
A29: 加投有上限 | B29: 单渠道单月 +20%，连续扩投不超过 2 个月，之后转人工复核
A30: 总盘不超支 | B30: 加投后总盘 ≤ 110%；释放预算优先转给比值最高的渠道，无人接就留池不硬花
A31: 口径唯一 | B31: LTV 用 12 个月毛利贡献（非收入）、CAC 用全成本；三数必须同月、同口径、同币种
A32: 合规 | B32: 客户 ID 加密存储、行为数据脱敏；暂停期间的再触达必须有用户明确同意
